gestalt/__init__.py
gestalt/provider.py
gestalt/utils.py
gestalt/vault.py
gestalt_cfg-3.4.6.dist-info/METADATA
gestalt_cfg-3.4.6.dist-info/WHEEL
gestalt_cfg-3.4.6.dist-info/RECORD
