Metadata-Version: 2.4
Name: gestalt-cfg
Version: 3.4.6
Summary: Gestalt is an opinionated, strongly typed, configuration library for Python 3.8+. Gestalt aims to simplify configuration loading, getting/setting, and management by letting the user focus on writing programs, and letting Gestalt check configuration types, location, and environment variable overrides.
Author-email: Clear Street <engineering@clearstreet.io>
License-Expression: MIT
Classifier: Development Status :: 5 - Production/Stable
Classifier: Intended Audience :: Developers
Classifier: License :: OSI Approved :: MIT License
Classifier: Operating System :: OS Independent
Classifier: Programming Language :: Python :: 3
Classifier: Programming Language :: Python :: 3 :: Only
Classifier: Programming Language :: Python :: 3.6
Classifier: Programming Language :: Python :: 3.7
Classifier: Programming Language :: Python :: 3.8
Classifier: Topic :: Software Development :: Libraries
Requires-Python: >=3.8
Requires-Dist: hvac<1.1.0,>=1.0.2
Requires-Dist: jsonpath-ng==1.5.3
Requires-Dist: python-dateutil>=2.8.0
Requires-Dist: pyyaml==6.0.1
Requires-Dist: retry==0.9.2
